{
  "name": "Address",
  "base": "PersistedModel",
  "strict": false,
  "idInjection": true,
  "options": {
    "validateUpsert": true,
    "mysql": {
      "schema": "LOOPBACK",
      "table": "zn_address"
    }
  },
  "properties": {
    "street": {
      "type": "string"
    },
    "city": {
      "type": "string"
    },
    "state": {
      "type": "string"
    },
    "zip": {
      "type": "string"
    },
    "country": {
      "type": "string"
    },
    "location": {
      "type": "geopoint",
      "comments": "39.281516,-76.580806"
    }
  },
  "validations": [],
  "relations": {},
  "acls": [],
  "methods": {}
}
